jk_jsonmodel/AbstractConstraint.py
jk_jsonmodel/JMLocation.py
jk_jsonmodel/JMMerger.py
jk_jsonmodel/JMRetriever.py
jk_jsonmodel/JsonParserRelaxedModel.py
jk_jsonmodel/__init__.py
jk_jsonmodel/constraints.py
jk_jsonmodel/jclasses.py
jk_jsonmodel-0.2024.7.15.dist-info/WHEEL
jk_jsonmodel-0.2024.7.15.dist-info/METADATA
jk_jsonmodel-0.2024.7.15.dist-info/RECORD
