Metadata-Version: 2.1
Name: jk_jsonmodel
Version: 0.2024.7.15
Summary: This python module provides a special parser for JSON files that produces a data model where each value is associated with the location it originated from in the source file.
Keywords: json,parsing,schema
Author-email: Jürgen Knauth <pubsrc@binary-overflow.de>
Maintainer-email: Jürgen Knauth <pubsrc@binary-overflow.de>
Requires-Python: >=3.8
Classifier: Development Status :: 5 - Production/Stable
Classifier: License :: OSI Approved :: Apache Software License
Classifier: Programming Language :: Python :: 3
Requires-Dist: jk_json
Requires-Dist: jk_prettyprintobj
